jobs_python_lib/__init__.py
jobs_python_lib/authorization.py
jobs_python_lib/constants.py
jobs_python_lib/graphql_response.py
jobs_python_lib/helpers.py
jobs_python_lib/postgres.py
jobs_python_lib/secrets_manager.py
jobs_python_lib_package-0.0.3.dist-info/LICENSE
jobs_python_lib_package-0.0.3.dist-info/METADATA
jobs_python_lib_package-0.0.3.dist-info/WHEEL
jobs_python_lib_package-0.0.3.dist-info/top_level.txt
jobs_python_lib_package-0.0.3.dist-info/RECORD
