Metadata-Version: 2.1
Name: jobs-python-lib-package
Version: 0.0.3
Summary: Jobs Engineering team commonly used Python files
Home-page: https://bitbucket.org/dhigroupinc/workspace/projects/JOBS
Author: Ian McCray
Author-email: ian.mccray@dhigroupinc.com
License: UNKNOWN
Project-URL: Bug Tracker, https://github.com/pypa/sampleproject/issues
Platform: UNKNOWN
Classifier: Programming Language :: Python :: 3
Classifier: License :: OSI Approved :: MIT License
Classifier: Operating System :: OS Independent
Requires-Python: >=3.6
License-File: LICENSE
